swegen/__init__.py
swegen/cli.py
swegen/config.py
swegen/analyze/__init__.py
swegen/analyze/classifier.py
swegen/analyze/classify_prompt.txt
swegen/analyze/models.py
swegen/analyze/run.py
swegen/analyze/verdict_prompt.txt
swegen/create/__init__.py
swegen/create/claude_code_runner.py
swegen/create/claude_code_utils.py
swegen/create/create.py
swegen/create/diff_utils.py
swegen/create/orchestrator.py
swegen/create/pr_fetcher.py
swegen/create/repo_cache.py
swegen/create/task_instruction.py
swegen/create/task_reference.py
swegen/create/task_skeleton.py
swegen/create/utils.py
swegen/farm/__init__.py
swegen/farm/farm_hand.py
swegen/farm/fetcher.py
swegen/farm/state.py
swegen/farm/stream_farm.py
swegen/tools/__init__.py
swegen/tools/harbor_runner.py
swegen/tools/validate.py
swegen/tools/validate_utils.py
swegen-0.1.0.dist-info/METADATA
swegen-0.1.0.dist-info/WHEEL
swegen-0.1.0.dist-info/entry_points.txt
swegen-0.1.0.dist-info/licenses/LICENSE
swegen-0.1.0.dist-info/RECORD
