Metadata-Version: 2.4
Name: swegen
Version: 0.1.0
Summary: Pipeline to convert GitHub PRs into Harbor tasks
Project-URL: Homepage, https://github.com/abundant-ai/swe-gen
Project-URL: Repository, https://github.com/abundant-ai/swe-gen
Project-URL: Issues, https://github.com/abundant-ai/swe-gen/issues
Author-email: Rishi Desai <rishi@abundant.ai>
License: Apache-2.0
License-File: LICENSE
Keywords: harbor,swe-bench,terminal-bench
Classifier: Development Status :: 3 - Alpha
Classifier: Intended Audience :: Developers
Classifier: License :: OSI Approved :: Apache Software License
Classifier: Programming Language :: Python :: 3
Classifier: Programming Language :: Python :: 3.12
Classifier: Topic :: Software Development :: Quality Assurance
Classifier: Topic :: Software Development :: Testing
Requires-Python: >=3.12
Requires-Dist: claude-agent-sdk>=0.1.20
Requires-Dist: click>=8.3.1
Requires-Dist: docker>=7.1.0
Requires-Dist: gitpython>=3.1.46
Requires-Dist: harbor>=0.1.41
Requires-Dist: openai>=2.15.0
Requires-Dist: pydantic>=2.12.5
Requires-Dist: pygithub>=2.8.1
Requires-Dist: python-dotenv>=1.2.1
Requires-Dist: pyyaml>=6.0.3
Requires-Dist: requests>=2.32.5
Requires-Dist: rich>=14.2.0
Requires-Dist: typer>=0.21.1
Provides-Extra: dev
Requires-Dist: black>=25.12.0; extra == 'dev'
Requires-Dist: pytest>=9.0.2; extra == 'dev'
Requires-Dist: ruff>=0.14.10; extra == 'dev'
